LICENSE
README.md
setup.py
ed_amino.egg-info/PKG-INFO
ed_amino.egg-info/SOURCES.txt
ed_amino.egg-info/dependency_links.txt
ed_amino.egg-info/requires.txt
ed_amino.egg-info/top_level.txt
edamino/__init__.py
edamino/api.py
edamino/bot.py
edamino/client.py
edamino/context.py
edamino/logger.py
edamino/objects.py
edamino/util.py