Metadata-Version: 2.1
Name: ed-amino
Version: 0.7.2.2
Summary: Async library for amino.
Home-page: https://github.com/SvytDola/edamino
Author: SvytDola
License: MIT
Keywords: edamino
Platform: UNKNOWN
Classifier: License :: OSI Approved :: MIT License
Classifier: Operating System :: Microsoft :: Windows
Classifier: Programming Language :: Python :: 3.8
Classifier: Programming Language :: Python :: 3.9
License-File: LICENSE
